enclave/__init__.py
enclave/_baseclient.py
enclave/_cross.py
enclave/_perps.py
enclave/_spot.py
enclave/client.py
enclave/models.py
enclave/wsclient.py
enclave-0.3.2.dist-info/LICENSE
enclave-0.3.2.dist-info/METADATA
enclave-0.3.2.dist-info/WHEEL
enclave-0.3.2.dist-info/RECORD
